terra/__init__.py
terra/terra.py
terra/data/Chondrites.csv
terra/data/model-lionel.txt
terra/data/seab_data.csv
terra/data/yale.txt
terra_2.0-0.2.dist-info/LICENSE
terra_2.0-0.2.dist-info/METADATA
terra_2.0-0.2.dist-info/WHEEL
terra_2.0-0.2.dist-info/top_level.txt
terra_2.0-0.2.dist-info/RECORD
