Metadata-Version: 2.1
Name: terra-2.0
Version: 0.2
Summary: Script to simulate planet formation or engulfment
Home-page: https://github.com/ramstojh/terra
Author: Jhon Yana
Author-email: ramstojh@alumni.usp.br
License: MIT
Platform: UNKNOWN
License-File: LICENSE
Requires-Dist: numpy
Requires-Dist: pandas
Requires-Dist: tqdm
Requires-Dist: astropy
Requires-Dist: matplotlib
